{
  "project_info": {
    "project_number": "158455647020",
    "project_id": "readindiacelebration-16f72",
    "storage_bucket": "readindiacelebration-16f72.appspot.com"
  },
  "client": [
    {
      "client_info": {
        "mobilesdk_app_id": "1:158455647020:android:69c0029dfe18a75eaffa89",
        "android_client_info": {
          "package_name": "com.example.ricmobile"
        }
      },
      "oauth_client": [
        {
          "client_id": "158455647020-kveeh9msr60ap0inkectne863ssbe7dp.apps.googleusercontent.com",
          "client_type": 3
        }
      ],
      "api_key": [
        {
          "current_key": "AIzaSyCvTgPxz9fOdg6Wh1yogDcchRWlEfQts2k"
        }
      ],
      "services": {
        "appinvite_service": {
          "other_platform_oauth_client": [
            {
              "client_id": "158455647020-kveeh9msr60ap0inkectne863ssbe7dp.apps.googleusercontent.com",
              "client_type": 3
            }
          ]
        }
      }
    }
  ],
  "configuration_version": "1"
}